xacro4sdf/__init__.py
xacro4sdf/common.xmacro
xacro4sdf/xacro4sdf.py
xacro4sdf/xml_format.py
xacro4sdf-2.1.0.dist-info/LICENSE
xacro4sdf-2.1.0.dist-info/METADATA
xacro4sdf-2.1.0.dist-info/WHEEL
xacro4sdf-2.1.0.dist-info/entry_points.txt
xacro4sdf-2.1.0.dist-info/top_level.txt
xacro4sdf-2.1.0.dist-info/RECORD
