Metadata-Version: 2.1
Name: xacro4sdf
Version: 2.1.0
Summary: a simple XML macro script for sdf, like ros/xacro which is desiged for urdf.
Home-page: https://github.com/gezp/xacro4sdf
Author: Zhenpeng Ge
Author-email: zhenpeng.ge@qq.com
License: MIT
Keywords: sdf,sdformat,xacro,gazebo,ignition
Platform: UNKNOWN
